tracetorch/__init__.py
tracetorch/functional/__init__.py
tracetorch/functional/_sample_softmax.py
tracetorch/functional/_sigmoid_inverse.py
tracetorch/functional/_softplus_inverse.py
tracetorch/loss/__init__.py
tracetorch/loss/_mse.py
tracetorch/loss/_reflect.py
tracetorch/plot/__init__.py
tracetorch/plot/_distributions.py
tracetorch/plot/_line_graph.py
tracetorch/plot/_measurement_manager.py
tracetorch/plot/_render_image.py
tracetorch/plot/_spike_train.py
tracetorch/snn/__init__.py
tracetorch/snn/_lif.py
tracetorch/snn/_lis.py
tracetorch/snn/_sequential.py
tracetorch-0.3.0.dist-info/licenses/LICENSE
tracetorch-0.3.0.dist-info/METADATA
tracetorch-0.3.0.dist-info/WHEEL
tracetorch-0.3.0.dist-info/top_level.txt
tracetorch-0.3.0.dist-info/RECORD
