Metadata-Version: 2.4
Name: tracetorch
Version: 0.3.0
Summary: An extension to PyTorch: SNN layers that function on traces.
Author-email: Yegor Men <yegor.mn@gmail.com>
License-Expression: Apache-2.0
Project-URL: Homepage, https://github.com/Yegor-men/tracetorch
Project-URL: Repository, https://github.com/Yegor-men/tracetorch
Project-URL: Issues, https://github.com/Yegor-men/tracetorch/issues
Project-URL: Documentation, https://yegor-men.github.io/tracetorch/
Classifier: Programming Language :: Python :: 3
Classifier: Operating System :: OS Independent
Classifier: Topic :: Scientific/Engineering :: Artificial Intelligence
Requires-Python: >=3.8
License-File: LICENSE
Requires-Dist: torch
Requires-Dist: numpy
Requires-Dist: matplotlib
Dynamic: license-file
